odoo/addons/hr_timesheet_purchase_order/README.rst
odoo/addons/hr_timesheet_purchase_order/__init__.py
odoo/addons/hr_timesheet_purchase_order/__manifest__.py
odoo/addons/hr_timesheet_purchase_order/data/hr_timesheet_cron.xml
odoo/addons/hr_timesheet_purchase_order/data/ir_actions_server.xml
odoo/addons/hr_timesheet_purchase_order/i18n/hr_timesheet_purchase_order.pot
odoo/addons/hr_timesheet_purchase_order/i18n/it.po
odoo/addons/hr_timesheet_purchase_order/models/__init__.py
odoo/addons/hr_timesheet_purchase_order/models/consts.py
odoo/addons/hr_timesheet_purchase_order/models/hr_employee_base.py
odoo/addons/hr_timesheet_purchase_order/models/hr_timesheet_recurrence.py
odoo/addons/hr_timesheet_purchase_order/models/hr_timesheet_sheet.py
odoo/addons/hr_timesheet_purchase_order/models/purchase_order.py
odoo/addons/hr_timesheet_purchase_order/models/res_company.py
odoo/addons/hr_timesheet_purchase_order/models/res_config_settings.py
odoo/addons/hr_timesheet_purchase_order/models/res_partner.py
odoo/addons/hr_timesheet_purchase_order/readme/CONFIGURE.rst
odoo/addons/hr_timesheet_purchase_order/readme/CONTRIBUTORS.rst
odoo/addons/hr_timesheet_purchase_order/readme/CREDITS.rst
odoo/addons/hr_timesheet_purchase_order/readme/DESCRIPTION.rst
odoo/addons/hr_timesheet_purchase_order/readme/USAGE.rst
odoo/addons/hr_timesheet_purchase_order/security/ir.model.access.csv
odoo/addons/hr_timesheet_purchase_order/static/description/icon.png
odoo/addons/hr_timesheet_purchase_order/static/description/index.html
odoo/addons/hr_timesheet_purchase_order/tests/__init__.py
odoo/addons/hr_timesheet_purchase_order/tests/common_po_recurrence.py
odoo/addons/hr_timesheet_purchase_order/tests/test_create_not_product.py
odoo/addons/hr_timesheet_purchase_order/tests/test_create_timesheet_po_recurrence.py
odoo/addons/hr_timesheet_purchase_order/tests/test_create_timesheet_purchase_order.py
odoo/addons/hr_timesheet_purchase_order/views/hr_employee_view.xml
odoo14_addon_hr_timesheet_purchase_order-14.0.1.1.0.dist-info/METADATA
odoo14_addon_hr_timesheet_purchase_order-14.0.1.1.0.dist-info/WHEEL
odoo14_addon_hr_timesheet_purchase_order-14.0.1.1.0.dist-info/top_level.txt
odoo14_addon_hr_timesheet_purchase_order-14.0.1.1.0.dist-info/RECORD
